cow/__init__.py
cow/admin.py
cow/api.py
cow/apps.py
cow/forms.py
cow/models.py
cow/urls.py
cow/views.py
cow/migrations/0001_initial.py
cow/migrations/__init__.py
cow/static/cow/css/cowbone.css
cow/static/cow/css/cowhide.css
cow/static/cow/css/pure-min.css
cow/static/cow/font/cowhide.eot
cow/static/cow/font/cowhide.svg
cow/static/cow/font/cowhide.ttf
cow/static/cow/font/cowhide.woff
cow/static/cow/tinymce/jquery.tinymce.min.js
cow/static/cow/tinymce/tinymce.min.js
cow/static/cow/tinymce/plugins/advlist/plugin.min.js
cow/static/cow/tinymce/plugins/anchor/plugin.min.js
cow/static/cow/tinymce/plugins/autolink/plugin.min.js
cow/static/cow/tinymce/plugins/autoresize/plugin.min.js
cow/static/cow/tinymce/plugins/autosave/plugin.min.js
cow/static/cow/tinymce/plugins/bbcode/plugin.min.js
cow/static/cow/tinymce/plugins/charmap/plugin.min.js
cow/static/cow/tinymce/plugins/code/plugin.min.js
cow/static/cow/tinymce/plugins/codesample/plugin.min.js
cow/static/cow/tinymce/plugins/codesample/css/prism.css
cow/static/cow/tinymce/plugins/colorpicker/plugin.min.js
cow/static/cow/tinymce/plugins/contextmenu/plugin.min.js
cow/static/cow/tinymce/plugins/directionality/plugin.min.js
cow/static/cow/tinymce/plugins/emoticons/plugin.min.js
cow/static/cow/tinymce/plugins/emoticons/img/smiley-cool.gif
cow/static/cow/tinymce/plugins/emoticons/img/smiley-cry.gif
cow/static/cow/tinymce/plugins/emoticons/img/smiley-embarassed.gif
cow/static/cow/tinymce/plugins/emoticons/img/smiley-foot-in-mouth.gif
cow/static/cow/tinymce/plugins/emoticons/img/smiley-frown.gif
cow/static/cow/tinymce/plugins/emoticons/img/smiley-innocent.gif
cow/static/cow/tinymce/plugins/emoticons/img/smiley-kiss.gif
cow/static/cow/tinymce/plugins/emoticons/img/smiley-laughing.gif
cow/static/cow/tinymce/plugins/emoticons/img/smiley-money-mouth.gif
cow/static/cow/tinymce/plugins/emoticons/img/smiley-sealed.gif
cow/static/cow/tinymce/plugins/emoticons/img/smiley-smile.gif
cow-1.0.7.dist-info/DESCRIPTION.rst
cow-1.0.7.dist-info/METADATA
cow-1.0.7.dist-info/RECORD
cow-1.0.7.dist-info/WHEEL
cow-1.0.7.dist-info/metadata.json
cow-1.0.7.dist-info/top_level.txt
