Metadata-Version: 2.0
Name: cow
Version: 1.0.7
Summary: Yuge heifer-like bloated CMS - now with more django, S3, Lambda friendliness!
Home-page: https://github.com/narfman0/cow
Author: Jon Robison
Author-email: narfman0@gmail.com
License: MIT
Keywords: django,cow,cms
Platform: UNKNOWN
Classifier: Development Status :: 4 - Beta
Classifier: Framework :: Django
Classifier: Framework :: Django :: 1.8
Classifier: Framework :: Django :: 1.9
Classifier: Framework :: Django :: 1.10
Classifier: Framework :: Django :: 1.11
Classifier: Intended Audience :: Developers
Classifier: License :: OSI Approved :: BSD License
Classifier: Natural Language :: English
Classifier: Programming Language :: Python :: 2
Classifier: Programming Language :: Python :: 2.7
Classifier: Programming Language :: Python :: 3
Classifier: Programming Language :: Python :: 3.5
Requires-Dist: django
Requires-Dist: djangorestframework
Requires-Dist: pillow
